sqlfluff_templater_schemachange/__init__.py
sqlfluff_templater_schemachange/sqlfluff-templater-schemachange.py
sqlfluff_templater_schemachange-0.1.1.dist-info/licenses/LICENSE
sqlfluff_templater_schemachange-0.1.1.dist-info/METADATA
sqlfluff_templater_schemachange-0.1.1.dist-info/WHEEL
sqlfluff_templater_schemachange-0.1.1.dist-info/entry_points.txt
sqlfluff_templater_schemachange-0.1.1.dist-info/top_level.txt
sqlfluff_templater_schemachange-0.1.1.dist-info/RECORD
