Metadata-Version: 2.4
Name: sqlfluff-templater-schemachange
Version: 0.1.1
Summary: A SQLFluff templater compatible with schemachange, supporting macros, env_var, and config loading.
Author-email: Thomas MacKay <mackay.thomas@gmail.com>
Maintainer-email: Thomas MacKay <mackay.thomas@gmail.com>
License: MIT
Project-URL: Homepage, https://github.com/MACKAT05/sqlfluff-templater-schemachange
Project-URL: Documentation, https://github.com/MACKAT05/sqlfluff-templater-schemachange
Project-URL: Repository, https://github.com/MACKAT05/sqlfluff-templater-schemachange
Project-URL: Bug Reports, https://github.com/MACKAT05/sqlfluff-templater-schemachange/issues
Keywords: sqlfluff,templater,schemachange,snowflake,database,linting
Classifier: Development Status :: 4 - Beta
Classifier: Intended Audience :: Developers
Classifier: License :: OSI Approved :: MIT License
Classifier: Operating System :: OS Independent
Classifier: Programming Language :: Python :: 3
Classifier: Programming Language :: Python :: 3.8
Classifier: Programming Language :: Python :: 3.9
Classifier: Programming Language :: Python :: 3.10
Classifier: Programming Language :: Python :: 3.11
Classifier: Topic :: Software Development :: Quality Assurance
Classifier: Topic :: Database
Requires-Python: >=3.8
License-File: LICENSE
Requires-Dist: sqlfluff>=2.0.0
Requires-Dist: PyYAML>=5.1
Requires-Dist: jinja2>=3.0.0
Provides-Extra: dev
Requires-Dist: black>=22.0.0; extra == "dev"
Requires-Dist: isort>=5.0.0; extra == "dev"
Requires-Dist: mypy>=0.950; extra == "dev"
Requires-Dist: bandit>=1.7.0; extra == "dev"
Requires-Dist: pytest>=7.0.0; extra == "dev"
Requires-Dist: pre-commit>=2.20.0; extra == "dev"
Dynamic: license-file
